python_osw_validation/__init__.py
python_osw_validation/extracted_data_validator.py
python_osw_validation/helpers.py
python_osw_validation/version.py
python_osw_validation/zipfile_handler.py
python_osw_validation/schema/opensidewalks.edges.schema-0.3.json
python_osw_validation/schema/opensidewalks.lines.schema-0.3.json
python_osw_validation/schema/opensidewalks.nodes.schema-0.3.json
python_osw_validation/schema/opensidewalks.points.schema-0.3.json
python_osw_validation/schema/opensidewalks.polygons.schema-0.3.json
python_osw_validation/schema/opensidewalks.schema-0.3.json
python_osw_validation/schema/opensidewalks.zones.schema-0.3.json
python_osw_validation-0.3.3.dist-info/licenses/LICENSE
python_osw_validation-0.3.3.dist-info/METADATA
python_osw_validation-0.3.3.dist-info/WHEEL
python_osw_validation-0.3.3.dist-info/top_level.txt
python_osw_validation-0.3.3.dist-info/RECORD
