Metadata-Version: 2.4
Name: python_osw_validation
Version: 0.3.3
Summary: Python library for OSW validation
Home-page: https://github.com/TaskarCenterAtUW/TDEI-python-lib-osw-validation
Author: Sujata Misra
Author-email: sujatam@gaussiansolutions.com
Project-URL: Documentation, https://github.com/TaskarCenterAtUW/TDEI-python-lib-osw-validation/blob/main/README.md
Project-URL: GitHub, https://github.com/TaskarCenterAtUW/TDEI-python-lib-osw-validation
Project-URL: Changelog, https://github.com/TaskarCenterAtUW/TDEI-python-lib-osw-validation/blob/main/CHANGELOG.md
Classifier: Programming Language :: Python :: 3
Classifier: License :: OSI Approved :: MIT License
Classifier: Operating System :: OS Independent
Requires-Python: >=3.10
License-File: LICENSE
Requires-Dist: jsonschema_rs==0.26.1
Requires-Dist: zipfile36==0.1.3
Requires-Dist: geopandas==0.14.4
Dynamic: author
Dynamic: author-email
Dynamic: classifier
Dynamic: description
Dynamic: description-content-type
Dynamic: home-page
Dynamic: license-file
Dynamic: project-url
Dynamic: requires-dist
Dynamic: requires-python
Dynamic: summary
